tesla_ce/__init__.py
tesla_ce/apps.py
tesla_ce/celery_app.py
tesla_ce/client.py
tesla_ce/error.py
tesla_ce/manage.py
tesla_ce/settings.py
tesla_ce/urls.py
tesla_ce/wsgi.py
tesla_ce/apps/__init__.py
tesla_ce/apps/api/__init__.py
tesla_ce/apps/api/apps.py
tesla_ce/apps/api/permissions.py
tesla_ce/apps/api/status.py
tesla_ce/apps/api/urls.py
tesla_ce/apps/api/utils.py
tesla_ce/apps/api/auth/__init__.py
tesla_ce/apps/api/auth/serializers.py
tesla_ce/apps/api/auth/urls.py
tesla_ce/apps/api/auth/views.py
tesla_ce/apps/api/v1/__init__.py
tesla_ce/apps/api/v1/urls.py
tesla_ce/apps/api/v1/serializers/__init__.py
tesla_ce/apps/api/v1/serializers/tep.py
tesla_ce/apps/api/v1/serializers/tip.py
tesla_ce/apps/api/v1/views/__init__.py
tesla_ce/apps/api/v1/views/tep.py
tesla_ce/apps/api/v1/views/tip.py
tesla_ce/apps/api/v2/__init__.py
tesla_ce/apps/api/v2/urls.py
tesla_ce/apps/api/v2/serializers/__init__.py
tesla_ce/apps/api/v2/serializers/admin/__init__.py
tesla_ce/apps/api/v2/serializers/admin/institution.py
tesla_ce/apps/api/v2/serializers/admin/instrument.py
tesla_ce/apps/api/v2/serializers/admin/provider.py
tesla_ce/apps/api/v2/serializers/admin/ui_option.py
tesla_ce/apps/api/v2/serializers/admin/user.py
tesla_ce/apps/api/v2/serializers/institution/__init__.py
tesla_ce/apps/api/v2/serializers/institution/activity.py
tesla_ce/apps/api/v2/serializers/institution/activity_instrument.py
tesla_ce/apps/api/v2/serializers/institution/activity_report.py
tesla_ce/apps/api/v2/serializers/institution/activity_report_audit.py
tesla_ce/apps/api/v2/serializers/institution/alert.py
tesla_ce/apps/api/v2/serializers/institution/course.py
tesla_ce/apps/api/v2/serializers/institution/course_group.py
tesla_ce/apps/api/v2/serializers/institution/course_instructor.py
tesla_ce/apps/api/v2/serializers/institution/course_learner.py
tesla_ce/apps/api/v2/serializers/institution/informed_consent.py
tesla_ce/apps/api/v2/serializers/institution/informed_consent_document.py
tesla_ce-1.0.10.dist-info/LICENSE
tesla_ce-1.0.10.dist-info/METADATA
tesla_ce-1.0.10.dist-info/WHEEL
tesla_ce-1.0.10.dist-info/entry_points.txt
tesla_ce-1.0.10.dist-info/top_level.txt
tesla_ce-1.0.10.dist-info/RECORD
