Metadata-Version: 2.1
Name: tesla-ce
Version: 1.0.10
Summary: TeSLA CE
Home-page: https://github.com/tesla-ce/core
Author: Xavier Baro
Author-email: xbaro@uoc.edu
License: UNKNOWN
Project-URL: Documentation, https://tesla-ce.github.io
Project-URL: Source, https://github.com/tesla-ce/core
Platform: UNKNOWN
Classifier: Programming Language :: Python :: 3
Classifier: License :: OSI Approved :: GNU Affero General Public License v3 or later (AGPLv3+)
Classifier: Operating System :: POSIX :: Linux
Requires-Python: >=3.7
License-File: LICENSE
Requires-Dist: alabaster (==0.7.13)
Requires-Dist: amqp (==5.1.1)
Requires-Dist: asgiref (==3.7.2)
Requires-Dist: async-timeout (==4.0.3)
Requires-Dist: attrs (==23.1.0)
Requires-Dist: babel (==2.12.1)
Requires-Dist: billiard (==4.1.0)
Requires-Dist: boto3 (==1.28.38)
Requires-Dist: botocore (==1.31.38)
Requires-Dist: celery (==5.3.1)
Requires-Dist: certifi (==2023.7.22)
Requires-Dist: charset-normalizer (==3.2.0)
Requires-Dist: click-didyoumean (==0.3.0)
Requires-Dist: click-plugins (==1.1.1)
Requires-Dist: click-repl (==0.3.0)
Requires-Dist: click (==8.1.7)
Requires-Dist: commonmark (==0.9.1)
Requires-Dist: coverage[toml] (==7.3.0)
Requires-Dist: cron-descriptor (==1.4.0)
Requires-Dist: django-cache-memoize (==0.1.10)
Requires-Dist: django-celery-beat (==2.5.0)
Requires-Dist: django-celery-results (==2.5.1)
Requires-Dist: django-configurations (==2.4.1)
Requires-Dist: django-cors-headers (==4.2.0)
Requires-Dist: django-filter (==23.2)
Requires-Dist: django-prometheus (==2.3.1)
Requires-Dist: django-redis (==5.3.0)
Requires-Dist: django-rest-auth (==0.9.5)
Requires-Dist: django-sslserver (==0.22)
Requires-Dist: django-storages (==1.13.2)
Requires-Dist: django-timezone-field (==6.0)
Requires-Dist: django (==4.2.4)
Requires-Dist: djangorestframework-datatables (==0.7.0)
Requires-Dist: djangorestframework-simplejwt (==5.3.0)
Requires-Dist: djangorestframework (==3.14.0)
Requires-Dist: docutils (==0.20.1)
Requires-Dist: drf-extensions (==0.7.1)
Requires-Dist: drf-yasg (==1.21.7)
Requires-Dist: exceptiongroup (==1.1.3)
Requires-Dist: gevent (==23.7.0)
Requires-Dist: greenlet (==2.0.2)
Requires-Dist: html-json-forms (==1.1.1)
Requires-Dist: hvac (==1.1.1)
Requires-Dist: idna (==3.4)
Requires-Dist: imagesize (==1.4.1)
Requires-Dist: inflection (==0.5.1)
Requires-Dist: iniconfig (==2.0.0)
Requires-Dist: jinja2 (==3.1.2)
Requires-Dist: jmespath (==1.0.1)
Requires-Dist: jsonschema-specifications (==2023.7.1)
Requires-Dist: jsonschema (==4.19.0)
Requires-Dist: kombu (==5.3.1)
Requires-Dist: markupsafe (==2.1.3)
Requires-Dist: packaging (==23.1)
Requires-Dist: pluggy (==1.3.0)
Requires-Dist: prometheus-client (==0.17.1)
Requires-Dist: prompt-toolkit (==3.0.39)
Requires-Dist: pygments (==2.16.1)
Requires-Dist: pyhcl (==0.4.4)
Requires-Dist: pyjwt (==2.8.0)
Requires-Dist: pytest-cov (==4.1.0)
Requires-Dist: pytest-dependency (==0.5.1)
Requires-Dist: pytest-django (==4.5.2)
Requires-Dist: pytest (==7.4.0)
Requires-Dist: python-crontab (==3.0.0)
Requires-Dist: python-dateutil (==2.8.2)
Requires-Dist: pytz (==2023.3)
Requires-Dist: pyyaml (==6.0.1)
Requires-Dist: rabbitmq-admin (==0.2)
Requires-Dist: recommonmark (==0.7.1)
Requires-Dist: redis (==5.0.0)
Requires-Dist: referencing (==0.30.2)
Requires-Dist: requests (==2.31.0)
Requires-Dist: rpds-py (==0.10.0)
Requires-Dist: s3transfer (==0.6.2)
Requires-Dist: sentry-sdk (==1.30.0)
Requires-Dist: simplejson (==3.17.4)
Requires-Dist: six (==1.16.0)
Requires-Dist: snowballstemmer (==2.2.0)
Requires-Dist: sphinx (==7.2.5)
Requires-Dist: sphinxcontrib-applehelp (==1.0.7)
Requires-Dist: sphinxcontrib-devhelp (==1.0.5)
Requires-Dist: sphinxcontrib-htmlhelp (==2.0.4)
Requires-Dist: sphinxcontrib-httpdomain (==1.8.1)
Requires-Dist: sphinxcontrib-jsmath (==1.0.1)
Requires-Dist: sphinxcontrib-qthelp (==1.0.6)
Requires-Dist: sphinxcontrib-serializinghtml (==1.1.9)
Requires-Dist: sqlparse (==0.4.4)
Requires-Dist: tomli (==2.0.1)
Requires-Dist: typing-extensions (==4.7.1)
Requires-Dist: tzdata (==2023.3)
Requires-Dist: uritemplate (==4.1.1)
Requires-Dist: urllib3 (==1.26.16)
Requires-Dist: vine (==5.0.0)
Requires-Dist: wcwidth (==0.2.6)
Requires-Dist: zope.event (==5.0)
Requires-Dist: zope.interface (==6.0)
Requires-Dist: mysqlclient
Provides-Extra: all
Requires-Dist: mysqlclient ; extra == 'all'
Requires-Dist: psycopg2 ; extra == 'all'
Provides-Extra: mysql
Requires-Dist: mysqlclient ; extra == 'mysql'
Provides-Extra: psql
Requires-Dist: psycopg2 ; extra == 'psql'
